mareposa
