Metadata-Version: 1.1
Name: mareposa
Version: 1.0.1
Summary: la maREPOsa automates creation of your remote GitHub & local git repositories, gitignore and README.md in one single line of code.
Home-page: https://github.com/RichStone/mareposa
Author: Richard Rich Steinmetz
Author-email: richard.had@hotmail.de
License: MIT
Platform: any
Classifier: Development Status :: 4 - Beta
Classifier: Environment :: Console
Classifier: Intended Audience :: Developers
Classifier: License :: OSI Approved :: MIT License
Classifier: Operating System :: POSIX
Classifier: Operating System :: MacOS
Classifier: Operating System :: Unix
Classifier: Operating System :: Microsoft :: Windows
Classifier: Programming Language :: Python
Classifier: Programming Language :: Python :: 2
Classifier: Programming Language :: Python :: 3
Classifier: Topic :: Software Development :: Libraries :: Python Modules
